marlware/__init__.py
marlware/rendering.py
marlware/warehouse.py
marlware/utils/__init__.py
marlware/utils/spaces.py
marlware/utils/wrappers.py
marlware-1.0.4.dist-info/LICENSE
marlware-1.0.4.dist-info/METADATA
marlware-1.0.4.dist-info/WHEEL
marlware-1.0.4.dist-info/top_level.txt
marlware-1.0.4.dist-info/RECORD
