Metadata-Version: 2.1
Name: marlware
Version: 1.0.4
Summary: Multi-Robot Warehouse environment for reinforcement learning
Home-page: https://github.com/semitable/robotic-warehouse
Author: Filippos Christianos
Classifier: Development Status :: 4 - Beta
Classifier: Intended Audience :: Developers
Classifier: Programming Language :: Python :: 3.7
License-File: LICENSE
Requires-Dist: numpy
Requires-Dist: gym (==0.21)
Requires-Dist: pyglet
Requires-Dist: networkx
Provides-Extra: test
Requires-Dist: pytest ; extra == 'test'
